cayenue/__init__.py
cayenue/enums.py
cayenue/glwidget.py
cayenue/main.py
cayenue/manager.py
cayenue/player.py
cayenue/server.py
cayenue/components/__init__.py
cayenue/components/comboselector.py
cayenue/components/directoryselector.py
cayenue/components/diskmanager.py
cayenue/components/fileselector.py
cayenue/components/infodialog.py
cayenue/components/progress.py
cayenue/components/target.py
cayenue/components/thresholdslider.py
cayenue/components/warningbar.py
cayenue/panels/__init__.py
cayenue/panels/audio/__init__.py
cayenue/panels/audio/audiopanel.py
cayenue/panels/audio/modules/__init__.py
cayenue/panels/audio/modules/sample.py
cayenue/panels/camera/__init__.py
cayenue/panels/camera/cameralist.py
cayenue/panels/camera/camerapanel.py
cayenue/panels/camera/datastructures.py
cayenue/panels/camera/imagetab.py
cayenue/panels/camera/logindialog.py
cayenue/panels/camera/networktab.py
cayenue/panels/camera/ptztab.py
cayenue/panels/camera/snapshot.py
cayenue/panels/camera/systemtab.py
cayenue/panels/camera/videotab.py
cayenue/panels/file/__init__.py
cayenue/panels/file/controlpanel.py
cayenue/panels/file/filepanel.py
cayenue/panels/file/searchdialog.py
cayenue/panels/file/treeview.py
cayenue/panels/picture/__init__.py
cayenue/panels/picture/picturepanel.py
cayenue/panels/settings/__init__.py
cayenue/panels/settings/alarm.py
cayenue/panels/settings/discover.py
cayenue/panels/settings/general.py
cayenue/panels/settings/proxy.py
cayenue/panels/settings/settingspanel.py
cayenue/panels/settings/storage.py
cayenue/panels/video/__init__.py
cayenue/panels/video/videopanel.py
cayenue/panels/video/modules/__init__.py
cayenue/panels/video/modules/motion.py
cayenue/panels/video/modules/settings.py
cayenue/panels/video/modules/yolox.py
cayenue/panels/video/modules/common/__init__.py
cayenue/panels/video/modules/yolox/__init__.py
cayenue/panels/video/modules/yolox/models/__init__.py
cayenue/panels/video/modules/yolox/models/build.py
cayenue-1.0.2.dist-info/licenses/LICENSE
cayenue-1.0.2.dist-info/METADATA
cayenue-1.0.2.dist-info/WHEEL
cayenue-1.0.2.dist-info/entry_points.txt
cayenue-1.0.2.dist-info/top_level.txt
cayenue-1.0.2.dist-info/RECORD
