Metadata-Version: 2.4
Name: cayenue
Version: 1.0.2
Summary: A client GUI for ONVIF
Author-email: Stephen Rhodes <sr99622@gmail.com>
License-Expression: Apache-2.0
Project-URL: Homepage, https://github.com/sr99622/Cayenue
Project-URL: Issues, https://github.com/sr99622/Cayenue/issues
Keywords: onvif,gui,qt,camera
Classifier: Development Status :: 5 - Production/Stable
Classifier: Intended Audience :: Developers
Classifier: Topic :: Software Development :: Build Tools
Classifier: Programming Language :: Python :: 3
Requires-Python: >=3.10
License-File: LICENSE
Requires-Dist: libonvif==3.2.8
Requires-Dist: avio==3.2.7
Requires-Dist: kankakee==1.0.4
Requires-Dist: numpy
Requires-Dist: loguru
Requires-Dist: opencv-python-headless
Requires-Dist: PyQt6-Qt6
Requires-Dist: PyQt6
Requires-Dist: requests
Dynamic: license-file
